ginja/__init__.py
ginja/__main__.py
ginja/cli.py
ginja/version.py
ginja-0.3.6.dist-info/METADATA
ginja-0.3.6.dist-info/WHEEL
ginja-0.3.6.dist-info/entry_points.txt
ginja-0.3.6.dist-info/top_level.txt
ginja-0.3.6.dist-info/RECORD
