Metadata-Version: 2.1
Name: ginja
Version: 0.3.6
Summary: CLI to batch-convert directories by Jinja2
Home-page: https://github.com/iamfat/ginja
Author: Jia Huang
Author-email: iamfat@gmail.com
License: MIT
Platform: UNKNOWN
Classifier: License :: OSI Approved :: MIT License
Classifier: Programming Language :: Python
Classifier: Programming Language :: Python :: 3
Classifier: Programming Language :: Python :: 3.5
Classifier: Programming Language :: Python :: 3.6
Classifier: Programming Language :: Python :: 3.7
Classifier: Programming Language :: Python :: Implementation :: CPython
Classifier: Programming Language :: Python :: Implementation :: PyPy
Requires-Python: >=3.5
Requires-Dist: python-dotenv (>=0.8.2)
Requires-Dist: click (>=6.7)
Requires-Dist: Jinja2
Requires-Dist: toml
Requires-Dist: PyYAML
